pg_engine/__init__.py
pg_engine/async_db.py
pg_engine/column.py
pg_engine/database.py
pg_engine/engine.py
pg_engine/errors.py
pg_engine/events.py
pg_engine/migrations.py
pg_engine/model.py
pg_engine/raw_sql.py
pg_engine/relation.py
pg_ready_engine-0.99.dist-info/METADATA
pg_ready_engine-0.99.dist-info/WHEEL
pg_ready_engine-0.99.dist-info/top_level.txt
pg_ready_engine-0.99.dist-info/RECORD
